flexmin/__init__.py
flexmin/flexmin_cli.py
flexmin/flexmin_srv.py
flexmin/flexmin_task.py
flexmin/run_checks.py
flexmin/assets/assets.txt
flexmin/assets/assets.yaml
flexmin/assets/config-examples.zip
flexmin/assets/config-templates.zip
flexmin/assets/configs.zip
flexmin/assets/py4web.zip
flexmin/assets/scripts.zip
flexmin/assets/system.zip
flexmin/utils/__init__.py
flexmin/utils/output_prep.py
flexmin/utils/simplepam.py
flexmin/utils/test.py
flexmin/utils/utilities.py
flexmin/utils/yamlconfigs.py
flexmin-0.4.2.dist-info/LICENSE
flexmin-0.4.2.dist-info/METADATA
flexmin-0.4.2.dist-info/WHEEL
flexmin-0.4.2.dist-info/entry_points.txt
flexmin-0.4.2.dist-info/top_level.txt
flexmin-0.4.2.dist-info/RECORD
