Metadata-Version: 2.1
Name: flexmin
Version: 0.4.2
Summary: A flexible system admin web portal
Home-page: https://www.futurscope.co.uk/flexmin
Author: Richard Cooke
Author-email: fm_1342@chrom3.co.uk
Maintainer: Richard Cooke
Maintainer-email: fm_1342@chrom3.co.uk
License: BSD
Project-URL: Source, https://bitbucket.org/futurscope/flexmin/src/master
Platform: linux
Classifier: Development Status :: 4 - Beta
Classifier: Environment :: Web Environment
Classifier: Intended Audience :: Developers
Classifier: Intended Audience :: System Administrators
Classifier: License :: OSI Approved :: BSD License
Classifier: Operating System :: POSIX :: Linux
Classifier: Programming Language :: Python
Classifier: Programming Language :: Python :: 3
Classifier: Topic :: System :: Systems Administration
License-File: LICENSE
Requires-Dist: click
Requires-Dist: py4web >=1.20221110
Requires-Dist: pyyaml
